[ {
  "homeTeam" : "Paranaense",
  "awayTeam" : "Flamengo",
  "picks" : [ "Alt (1.43 - 85.5%)" ],
  "score" : "1-1",
  "statuses" : {
    "Alt (1.43 - 85.5%)" : "won"
  }
}, {
  "homeTeam" : "Manta FC",
  "awayTeam" : "CS Emelec",
  "picks" : [ "Alt (1.36 - 81.5%)" ],
  "score" : "0-0",
  "statuses" : {
    "Alt (1.36 - 81.5%)" : "won"
  }
}, {
  "homeTeam" : "Spokane Velocity FC",
  "awayTeam" : "Las Vegas Li",
  "picks" : [ "Var (1.33 - 74.6%)" ],
  "score" : "-",
  "statuses" : {
    "Var (1.33 - 74.6%)" : "pending"
  }
}, {
  "homeTeam" : "Deportes Concepcion",
  "awayTeam" : "Everton DV",
  "picks" : [ "Alt (1.41 - 70.0%)" ],
  "score" : "0-2",
  "statuses" : {
    "Alt (1.41 - 70.0%)" : "won"
  }
}, {
  "homeTeam" : "Independiente Yumbo",
  "awayTeam" : "R Aguilas",
  "picks" : [ "Alt (1.39 - 69.8%)" ],
  "score" : "1-4",
  "statuses" : {
    "Alt (1.39 - 69.8%)" : "lost"
  }
}, {
  "homeTeam" : "CD Fas",
  "awayTeam" : "Municipal Li",
  "picks" : [ "Alt (1.56 - 62.7%)" ],
  "score" : "2-0",
  "statuses" : {
    "Alt (1.56 - 62.7%)" : "won"
  }
}, {
  "homeTeam" : "Vancouver Langley FC",
  "awayTeam" : "Cavalry FC",
  "picks" : [ "Alt (1.54 - 73.6%)" ],
  "score" : "-",
  "statuses" : {
    "Alt (1.54 - 73.6%)" : "pending"
  }
}, {
  "homeTeam" : "Kudrivka Irpin",
  "awayTeam" : "LNZ Cherkasy",
  "picks" : [ "Alt (1.43 - 76.7%)" ],
  "score" : "-",
  "statuses" : {
    "Alt (1.43 - 76.7%)" : "pending"
  }
}, {
  "homeTeam" : "Al Shabab",
  "awayTeam" : "Al Seeb",
  "picks" : [ "MS2 (1.77 - 61.7%)" ],
  "score" : "-",
  "statuses" : {
    "MS2 (1.77 - 61.7%)" : "pending"
  }
}, {
  "homeTeam" : "Al",
  "awayTeam" : "Khaboora",
  "picks" : [ "Alt (1.33 - 78.8%)" ],
  "score" : "-",
  "statuses" : {
    "Alt (1.33 - 78.8%)" : "pending"
  }
}, {
  "homeTeam" : "Bahla Club",
  "awayTeam" : "Al Nahda",
  "picks" : [ "Alt (1.38 - 79.3%)" ],
  "score" : "-",
  "statuses" : {
    "Alt (1.38 - 79.3%)" : "pending"
  }
}, {
  "homeTeam" : "Oman FC",
  "awayTeam" : "SUR SC",
  "picks" : [ "Alt (1.34 - 74.5%)" ],
  "score" : "-",
  "statuses" : {
    "Alt (1.34 - 74.5%)" : "pending"
  }
}, {
  "homeTeam" : "Sohar",
  "awayTeam" : "Saham",
  "picks" : [ "Alt (1.46 - 69.3%)" ],
  "score" : "-",
  "statuses" : {
    "Alt (1.46 - 69.3%)" : "pending"
  }
}, {
  "homeTeam" : "Stara Zagora",
  "awayTeam" : "FK Septemvri Sofia",
  "picks" : [ "Alt (1.49 - 59.4%)" ],
  "score" : "-",
  "statuses" : {
    "Alt (1.49 - 59.4%)" : "pending"
  }
}, {
  "homeTeam" : "IK Oddevold",
  "awayTeam" : "Orebro SK",
  "picks" : [ "Var (1.47 - 57.4%)" ],
  "score" : "-",
  "statuses" : {
    "Var (1.47 - 57.4%)" : "pending"
  }
}, {
  "homeTeam" : "Aarau",
  "awayTeam" : "Grasshoppers",
  "picks" : [ "Üst (1.51 - 78.2%)" ],
  "score" : "-",
  "statuses" : {
    "Üst (1.51 - 78.2%)" : "pending"
  }
} ]