[ {
  "homeTeam" : "South Dakota",
  "awayTeam" : "Metropolitan",
  "homeStats" : {
    "avgPointsFor" : 75.16666666666667,
    "avgPointsAgainst" : 87.66666666666667,
    "avgTotalPoints" : 162.83333333333334,
    "ppg" : 1.1666666666666667,
    "empty" : false
  },
  "awayStats" : {
    "avgPointsFor" : 75.33333333333333,
    "avgPointsAgainst" : 83.33333333333333,
    "avgTotalPoints" : 158.66666666666666,
    "ppg" : 1.1666666666666667,
    "empty" : false
  },
  "odds" : {
    "ms1" : 1.41,
    "ms2" : 1.95,
    "h1Value" : 0.0,
    "h2Value" : 0.0,
    "h1" : 0.0,
    "h2" : 0.0,
    "hOverUnderValue" : 154.5,
    "over" : 1.63,
    "under" : 1.64
  },
  "avgPointsForHome" : 75.4,
  "avgPointsForAway" : 81.4,
  "h2hAvgTotalPoints" : 156.8
}, {
  "homeTeam" : "Fort Hays St",
  "awayTeam" : "Newman Jets",
  "homeStats" : {
    "avgPointsFor" : 63.0,
    "avgPointsAgainst" : 65.16666666666667,
    "avgTotalPoints" : 128.16666666666666,
    "ppg" : 1.3333333333333333,
    "empty" : false
  },
  "awayStats" : {
    "avgPointsFor" : 62.833333333333336,
    "avgPointsAgainst" : 88.16666666666667,
    "avgTotalPoints" : 151.0,
    "ppg" : 1.0,
    "empty" : false
  },
  "odds" : {
    "ms1" : 0.0,
    "ms2" : 12.3,
    "h1Value" : 0.0,
    "h2Value" : 0.0,
    "h1" : 0.0,
    "h2" : 0.0,
    "hOverUnderValue" : 141.5,
    "over" : 1.62,
    "under" : 1.65
  },
  "avgPointsForHome" : 70.0,
  "avgPointsForAway" : 60.333333333333336,
  "h2hAvgTotalPoints" : 130.33333333333334
}, {
  "homeTeam" : "UC Davis Agg",
  "awayTeam" : "Long Beach S",
  "homeStats" : {
    "avgPointsFor" : 72.5,
    "avgPointsAgainst" : 72.16666666666667,
    "avgTotalPoints" : 144.66666666666666,
    "ppg" : 1.6666666666666667,
    "empty" : false
  },
  "awayStats" : {
    "avgPointsFor" : 71.83333333333333,
    "avgPointsAgainst" : 78.0,
    "avgTotalPoints" : 149.83333333333334,
    "ppg" : 1.0,
    "empty" : false
  },
  "odds" : {
    "ms1" : 1.24,
    "ms2" : 2.38,
    "h1Value" : 0.0,
    "h2Value" : 4.5,
    "h1" : 1.6,
    "h2" : 1.66,
    "hOverUnderValue" : 149.5,
    "over" : 1.64,
    "under" : 1.63
  },
  "avgPointsForHome" : 72.8,
  "avgPointsForAway" : 74.6,
  "h2hAvgTotalPoints" : 147.4
}, {
  "homeTeam" : "Union TN Bul",
  "awayTeam" : "Alabama Hunt",
  "homeStats" : {
    "avgPointsFor" : 69.0,
    "avgPointsAgainst" : 74.83333333333333,
    "avgTotalPoints" : 143.83333333333334,
    "ppg" : 1.3333333333333333,
    "empty" : false
  },
  "awayStats" : {
    "avgPointsFor" : 79.66666666666667,
    "avgPointsAgainst" : 74.83333333333333,
    "avgTotalPoints" : 154.5,
    "ppg" : 1.6666666666666667,
    "empty" : false
  },
  "odds" : {
    "ms1" : 3.22,
    "ms2" : 1.1,
    "h1Value" : 0.0,
    "h2Value" : 0.0,
    "h1" : 0.0,
    "h2" : 0.0,
    "hOverUnderValue" : 153.5,
    "over" : 1.63,
    "under" : 1.64
  },
  "avgPointsForHome" : 73.6,
  "avgPointsForAway" : 83.0,
  "h2hAvgTotalPoints" : 156.6
}, {
  "homeTeam" : "Colorado Mes",
  "awayTeam" : "New Mexico H",
  "homeStats" : {
    "avgPointsFor" : 86.66666666666667,
    "avgPointsAgainst" : 72.0,
    "avgTotalPoints" : 158.66666666666666,
    "ppg" : 2.0,
    "empty" : false
  },
  "awayStats" : {
    "avgPointsFor" : 85.5,
    "avgPointsAgainst" : 79.66666666666667,
    "avgTotalPoints" : 165.16666666666666,
    "ppg" : 1.5,
    "empty" : false
  },
  "odds" : {
    "ms1" : 0.0,
    "ms2" : 4.14,
    "h1Value" : 0.0,
    "h2Value" : 0.0,
    "h1" : 0.0,
    "h2" : 0.0,
    "hOverUnderValue" : 152.5,
    "over" : 1.63,
    "under" : 1.64
  },
  "avgPointsForHome" : 93.0,
  "avgPointsForAway" : 82.0,
  "h2hAvgTotalPoints" : 175.0
}, {
  "homeTeam" : "Pepperdine W",
  "awayTeam" : "Loyola Marym",
  "homeStats" : {
    "avgPointsFor" : 69.0,
    "avgPointsAgainst" : 86.16666666666667,
    "avgTotalPoints" : 155.16666666666666,
    "ppg" : 1.0,
    "empty" : false
  },
  "awayStats" : {
    "avgPointsFor" : 71.16666666666667,
    "avgPointsAgainst" : 74.66666666666667,
    "avgTotalPoints" : 145.83333333333334,
    "ppg" : 1.3333333333333333,
    "empty" : false
  },
  "odds" : {
    "ms1" : 2.63,
    "ms2" : 1.18,
    "h1Value" : 6.5,
    "h2Value" : 0.0,
    "h1" : 1.59,
    "h2" : 1.67,
    "hOverUnderValue" : 147.5,
    "over" : 1.62,
    "under" : 1.65
  },
  "avgPointsForHome" : 68.75,
  "avgPointsForAway" : 73.25,
  "h2hAvgTotalPoints" : 142.0
}, {
  "homeTeam" : "Alabama A&M",
  "awayTeam" : "Mississippi",
  "homeStats" : {
    "avgPointsFor" : 70.33333333333333,
    "avgPointsAgainst" : 72.16666666666667,
    "avgTotalPoints" : 142.5,
    "ppg" : 1.5,
    "empty" : false
  },
  "awayStats" : {
    "avgPointsFor" : 66.16666666666667,
    "avgPointsAgainst" : 78.33333333333333,
    "avgTotalPoints" : 144.5,
    "ppg" : 1.0,
    "empty" : false
  },
  "odds" : {
    "ms1" : 0.0,
    "ms2" : 10.35,
    "h1Value" : 0.0,
    "h2Value" : 15.5,
    "h1" : 1.65,
    "h2" : 1.62,
    "hOverUnderValue" : 139.5,
    "over" : 1.65,
    "under" : 1.62
  },
  "avgPointsForHome" : 78.0,
  "avgPointsForAway" : 63.0,
  "h2hAvgTotalPoints" : 141.0
}, {
  "homeTeam" : "Lafayette C.",
  "awayTeam" : "Lehigh Mount",
  "homeStats" : {
    "avgPointsFor" : 62.333333333333336,
    "avgPointsAgainst" : 66.83333333333333,
    "avgTotalPoints" : 129.16666666666666,
    "ppg" : 1.5,
    "empty" : false
  },
  "awayStats" : {
    "avgPointsFor" : 70.16666666666667,
    "avgPointsAgainst" : 70.0,
    "avgTotalPoints" : 140.16666666666666,
    "ppg" : 1.3333333333333333,
    "empty" : false
  },
  "odds" : {
    "ms1" : 1.56,
    "ms2" : 1.71,
    "h1Value" : 0.0,
    "h2Value" : 1.5,
    "h1" : 1.66,
    "h2" : 1.6,
    "hOverUnderValue" : 140.5,
    "over" : 1.6,
    "under" : 1.66
  },
  "avgPointsForHome" : 62.0,
  "avgPointsForAway" : 71.83333333333333,
  "h2hAvgTotalPoints" : 133.83333333333334
}, {
  "homeTeam" : "Bowling Gree",
  "awayTeam" : "Toledo Rocke",
  "homeStats" : {
    "avgPointsFor" : 68.0,
    "avgPointsAgainst" : 69.83333333333333,
    "avgTotalPoints" : 137.83333333333334,
    "ppg" : 1.3333333333333333,
    "empty" : false
  },
  "awayStats" : {
    "avgPointsFor" : 76.66666666666667,
    "avgPointsAgainst" : 74.16666666666667,
    "avgTotalPoints" : 150.83333333333334,
    "ppg" : 1.5,
    "empty" : false
  },
  "odds" : {
    "ms1" : 1.34,
    "ms2" : 2.09,
    "h1Value" : 0.0,
    "h2Value" : 3.5,
    "h1" : 1.63,
    "h2" : 1.64,
    "hOverUnderValue" : 150.5,
    "over" : 1.63,
    "under" : 1.64
  },
  "avgPointsForHome" : 74.33333333333333,
  "avgPointsForAway" : 78.66666666666667,
  "h2hAvgTotalPoints" : 153.0
}, {
  "homeTeam" : "E.Washington",
  "awayTeam" : "Weber State",
  "homeStats" : {
    "avgPointsFor" : 79.0,
    "avgPointsAgainst" : 75.5,
    "avgTotalPoints" : 154.5,
    "ppg" : 1.6666666666666667,
    "empty" : false
  },
  "awayStats" : {
    "avgPointsFor" : 81.33333333333333,
    "avgPointsAgainst" : 81.16666666666667,
    "avgTotalPoints" : 162.5,
    "ppg" : 1.5,
    "empty" : false
  },
  "odds" : {
    "ms1" : 1.4,
    "ms2" : 1.97,
    "h1Value" : 0.0,
    "h2Value" : 2.5,
    "h1" : 1.59,
    "h2" : 1.68,
    "hOverUnderValue" : 154.5,
    "over" : 1.6,
    "under" : 1.66
  },
  "avgPointsForHome" : 76.33333333333333,
  "avgPointsForAway" : 73.83333333333333,
  "h2hAvgTotalPoints" : 150.16666666666666
}, {
  "homeTeam" : "Central Mich",
  "awayTeam" : "Northern Ill",
  "homeStats" : {
    "avgPointsFor" : 77.16666666666667,
    "avgPointsAgainst" : 74.83333333333333,
    "avgTotalPoints" : 152.0,
    "ppg" : 1.3333333333333333,
    "empty" : false
  },
  "awayStats" : {
    "avgPointsFor" : 67.16666666666667,
    "avgPointsAgainst" : 71.66666666666667,
    "avgTotalPoints" : 138.83333333333334,
    "ppg" : 1.3333333333333333,
    "empty" : false
  },
  "odds" : {
    "ms1" : 1.28,
    "ms2" : 2.27,
    "h1Value" : 0.0,
    "h2Value" : 4.5,
    "h1" : 1.65,
    "h2" : 1.62,
    "hOverUnderValue" : 146.5,
    "over" : 1.67,
    "under" : 1.6
  },
  "avgPointsForHome" : 68.8,
  "avgPointsForAway" : 66.8,
  "h2hAvgTotalPoints" : 135.6
}, {
  "homeTeam" : "Southwest Mi",
  "awayTeam" : "Concordia-St",
  "homeStats" : {
    "avgPointsFor" : 69.83333333333333,
    "avgPointsAgainst" : 63.166666666666664,
    "avgTotalPoints" : 133.0,
    "ppg" : 1.3333333333333333,
    "empty" : false
  },
  "awayStats" : {
    "avgPointsFor" : 85.66666666666667,
    "avgPointsAgainst" : 78.16666666666667,
    "avgTotalPoints" : 163.83333333333334,
    "ppg" : 1.6666666666666667,
    "empty" : false
  },
  "odds" : {
    "ms1" : 1.24,
    "ms2" : 2.37,
    "h1Value" : 0.0,
    "h2Value" : 0.0,
    "h1" : 0.0,
    "h2" : 0.0,
    "hOverUnderValue" : 153.5,
    "over" : 1.65,
    "under" : 1.62
  },
  "avgPointsForHome" : 80.0,
  "avgPointsForAway" : 78.75,
  "h2hAvgTotalPoints" : 158.75
}, {
  "homeTeam" : "Southern Ind",
  "awayTeam" : "Tennessee Te",
  "homeStats" : {
    "avgPointsFor" : 65.33333333333333,
    "avgPointsAgainst" : 72.33333333333333,
    "avgTotalPoints" : 137.66666666666666,
    "ppg" : 1.1666666666666667,
    "empty" : false
  },
  "awayStats" : {
    "avgPointsFor" : 75.33333333333333,
    "avgPointsAgainst" : 71.5,
    "avgTotalPoints" : 146.83333333333334,
    "ppg" : 1.5,
    "empty" : false
  },
  "odds" : {
    "ms1" : 1.62,
    "ms2" : 1.65,
    "h1Value" : 0.0,
    "h2Value" : 1.5,
    "h1" : 1.72,
    "h2" : 1.56,
    "hOverUnderValue" : 139.5,
    "over" : 1.64,
    "under" : 1.63
  },
  "avgPointsForHome" : 66.6,
  "avgPointsForAway" : 68.8,
  "h2hAvgTotalPoints" : 135.4
}, {
  "homeTeam" : "Nebraska–Kea",
  "awayTeam" : "Emporia Stat",
  "homeStats" : {
    "avgPointsFor" : 73.66666666666667,
    "avgPointsAgainst" : 83.16666666666667,
    "avgTotalPoints" : 156.83333333333334,
    "ppg" : 1.3333333333333333,
    "empty" : false
  },
  "awayStats" : {
    "avgPointsFor" : 63.5,
    "avgPointsAgainst" : 78.66666666666667,
    "avgTotalPoints" : 142.16666666666666,
    "ppg" : 1.1666666666666667,
    "empty" : false
  },
  "odds" : {
    "ms1" : 1.44,
    "ms2" : 1.89,
    "h1Value" : 0.0,
    "h2Value" : 0.0,
    "h1" : 0.0,
    "h2" : 0.0,
    "hOverUnderValue" : 158.5,
    "over" : 1.66,
    "under" : 1.61
  },
  "avgPointsForHome" : 73.25,
  "avgPointsForAway" : 75.25,
  "h2hAvgTotalPoints" : 148.5
}, {
  "homeTeam" : "Texas S.",
  "awayTeam" : "Grambling St",
  "homeStats" : {
    "avgPointsFor" : 79.66666666666667,
    "avgPointsAgainst" : 73.0,
    "avgTotalPoints" : 152.66666666666666,
    "ppg" : 1.5,
    "empty" : false
  },
  "awayStats" : {
    "avgPointsFor" : 62.5,
    "avgPointsAgainst" : 61.166666666666664,
    "avgTotalPoints" : 123.66666666666667,
    "ppg" : 1.5,
    "empty" : false
  },
  "odds" : {
    "ms1" : 1.63,
    "ms2" : 1.64,
    "h1Value" : 0.0,
    "h2Value" : 1.5,
    "h1" : 1.73,
    "h2" : 1.54,
    "hOverUnderValue" : 139.5,
    "over" : 1.6,
    "under" : 1.66
  },
  "avgPointsForHome" : 62.333333333333336,
  "avgPointsForAway" : 65.66666666666667,
  "h2hAvgTotalPoints" : 128.0
}, {
  "homeTeam" : "Iowa",
  "awayTeam" : "Purdue",
  "homeStats" : {
    "avgPointsFor" : 75.83333333333333,
    "avgPointsAgainst" : 70.16666666666667,
    "avgTotalPoints" : 146.0,
    "ppg" : 1.8333333333333333,
    "empty" : false
  },
  "awayStats" : {
    "avgPointsFor" : 74.16666666666667,
    "avgPointsAgainst" : 70.66666666666667,
    "avgTotalPoints" : 144.83333333333334,
    "ppg" : 1.3333333333333333,
    "empty" : false
  },
  "odds" : {
    "ms1" : 1.72,
    "ms2" : 1.55,
    "h1Value" : 1.5,
    "h2Value" : 0.0,
    "h1" : 1.62,
    "h2" : 1.65,
    "hOverUnderValue" : 141.5,
    "over" : 1.61,
    "under" : 1.65
  },
  "avgPointsForHome" : 71.5,
  "avgPointsForAway" : 78.66666666666667,
  "h2hAvgTotalPoints" : 150.16666666666666
}, {
  "homeTeam" : "F. Bulldogs",
  "awayTeam" : "Air Force F.",
  "homeStats" : {
    "avgPointsFor" : 74.16666666666667,
    "avgPointsAgainst" : 78.16666666666667,
    "avgTotalPoints" : 152.33333333333334,
    "ppg" : 1.3333333333333333,
    "empty" : false
  },
  "awayStats" : {
    "avgPointsFor" : 58.833333333333336,
    "avgPointsAgainst" : 86.0,
    "avgTotalPoints" : 144.83333333333334,
    "ppg" : 1.0,
    "empty" : false
  },
  "odds" : {
    "ms1" : 0.0,
    "ms2" : 8.46,
    "h1Value" : 0.0,
    "h2Value" : 15.5,
    "h1" : 1.66,
    "h2" : 1.6,
    "hOverUnderValue" : 142.5,
    "over" : 1.65,
    "under" : 1.62
  },
  "avgPointsForHome" : 73.2,
  "avgPointsForAway" : 64.8,
  "h2hAvgTotalPoints" : 138.0
}, {
  "homeTeam" : "Idaho Vandal",
  "awayTeam" : "Idaho State",
  "homeStats" : {
    "avgPointsFor" : 72.33333333333333,
    "avgPointsAgainst" : 75.16666666666667,
    "avgTotalPoints" : 147.5,
    "ppg" : 1.1666666666666667,
    "empty" : false
  },
  "awayStats" : {
    "avgPointsFor" : 68.83333333333333,
    "avgPointsAgainst" : 79.0,
    "avgTotalPoints" : 147.83333333333334,
    "ppg" : 1.0,
    "empty" : false
  },
  "odds" : {
    "ms1" : 1.12,
    "ms2" : 2.99,
    "h1Value" : 0.0,
    "h2Value" : 6.5,
    "h1" : 1.59,
    "h2" : 1.68,
    "hOverUnderValue" : 147.5,
    "over" : 1.66,
    "under" : 1.6
  },
  "avgPointsForHome" : 63.6,
  "avgPointsForAway" : 69.8,
  "h2hAvgTotalPoints" : 133.4
}, {
  "homeTeam" : "North Caroli",
  "awayTeam" : "Wofford",
  "homeStats" : {
    "avgPointsFor" : 73.83333333333333,
    "avgPointsAgainst" : 76.16666666666667,
    "avgTotalPoints" : 150.0,
    "ppg" : 1.5,
    "empty" : false
  },
  "awayStats" : {
    "avgPointsFor" : 78.5,
    "avgPointsAgainst" : 74.66666666666667,
    "avgTotalPoints" : 153.16666666666666,
    "ppg" : 1.6666666666666667,
    "empty" : false
  },
  "odds" : {
    "ms1" : 1.88,
    "ms2" : 1.44,
    "h1Value" : 2.5,
    "h2Value" : 0.0,
    "h1" : 1.62,
    "h2" : 1.65,
    "hOverUnderValue" : 155.5,
    "over" : 1.65,
    "under" : 1.61
  },
  "avgPointsForHome" : 66.66666666666667,
  "avgPointsForAway" : 65.16666666666667,
  "h2hAvgTotalPoints" : 131.83333333333334
}, {
  "homeTeam" : "Eastern New",
  "awayTeam" : "Texas Dallas",
  "homeStats" : {
    "avgPointsFor" : 85.66666666666667,
    "avgPointsAgainst" : 76.16666666666667,
    "avgTotalPoints" : 161.83333333333334,
    "ppg" : 2.0,
    "empty" : false
  },
  "awayStats" : {
    "avgPointsFor" : 68.5,
    "avgPointsAgainst" : 82.66666666666667,
    "avgTotalPoints" : 151.16666666666666,
    "ppg" : 1.1666666666666667,
    "empty" : false
  },
  "odds" : {
    "ms1" : 0.0,
    "ms2" : 12.3,
    "h1Value" : 0.0,
    "h2Value" : 0.0,
    "h1" : 0.0,
    "h2" : 0.0,
    "hOverUnderValue" : 158.5,
    "over" : 1.63,
    "under" : 1.64
  },
  "avgPointsForHome" : 90.0,
  "avgPointsForAway" : 83.0,
  "h2hAvgTotalPoints" : 173.0
} ]