[ {
  "homeTeam" : "Detroit",
  "awayTeam" : "Houston",
  "picks" : [ "218.5 Alt (1.6 - 59.8%)" ],
  "score" : "-",
  "statuses" : {
    "218.5 Alt (1.6 - 59.8%)" : "pending"
  }
}, {
  "homeTeam" : "Penarol Mar",
  "awayTeam" : "Obras Sanita",
  "picks" : [ "MS1 (1.62 - 86.7%)" ],
  "score" : "-",
  "statuses" : {
    "MS1 (1.62 - 86.7%)" : "pending"
  }
}, {
  "homeTeam" : "Cleveland",
  "awayTeam" : "Sacramento",
  "picks" : [ "233.5 Üst (1.65 - 55.2%)" ],
  "score" : "-",
  "statuses" : {
    "233.5 Üst (1.65 - 55.2%)" : "pending"
  }
}, {
  "homeTeam" : "Atlanta",
  "awayTeam" : "Phoenix",
  "picks" : [ "MS2 (1.39 - 63.4%)" ],
  "score" : "-",
  "statuses" : {
    "MS2 (1.39 - 63.4%)" : "pending"
  }
}, {
  "homeTeam" : "Memphis",
  "awayTeam" : "New Orleans",
  "picks" : [ "239.5 Alt (1.65 - 70.9%)" ],
  "score" : "-",
  "statuses" : {
    "239.5 Alt (1.65 - 70.9%)" : "pending"
  }
}, {
  "homeTeam" : "Diamond Dolphins",
  "awayTeam" : "Seahorses Mikawa",
  "picks" : [ "159.5 Alt (1.63 - 56.7%)" ],
  "score" : "-",
  "statuses" : {
    "159.5 Alt (1.63 - 56.7%)" : "pending"
  }
} ]