[ {
  "homeTeam" : "New York (K)",
  "awayTeam" : "Phoenix (K)",
  "score" : "84-74"
}, {
  "homeTeam" : "Chicago Sky (K)",
  "awayTeam" : "Toronto Tempo (K)",
  "score" : "104-111"
}, {
  "homeTeam" : "Minnesota (K)",
  "awayTeam" : "Atlanta (K)",
  "score" : "96-81"
}, {
  "homeTeam" : "Portland Fire (K)",
  "awayTeam" : "Connecticut (K)",
  "score" : "71-61"
}, {
  "homeTeam" : "Seattle (K)",
  "awayTeam" : "Was Mystics (K)",
  "score" : "64-78"
}, {
  "homeTeam" : "Sport Club Do Recife (K)",
  "awayTeam" : "Sao Jose D. C. (K)",
  "score" : "48-67"
}, {
  "homeTeam" : "Toros de Torreon",
  "awayTeam" : "Halcones de Ciudad Obregon",
  "score" : "106-84"
}, {
  "homeTeam" : "Caballeros de Culiacan",
  "awayTeam" : "Astros",
  "score" : "87-95"
}, {
  "homeTeam" : "Adelitas de C. (K)",
  "awayTeam" : "Panteras Agua. (K)",
  "score" : "86-82"
}, {
  "homeTeam" : "Mets de Guaynabo",
  "awayTeam" : "Indios de Mayaguez",
  "score" : "91-85"
}, {
  "homeTeam" : "Criollas de Caguas",
  "awayTeam" : "Piratas de Quebradillas",
  "score" : "99-81"
}, {
  "homeTeam" : "Trabzonspor",
  "awayTeam" : "Bahçeşehir Koleji",
  "score" : "78-94"
}, {
  "homeTeam" : "AL Shabab (Bae)",
  "awayTeam" : "AL Bataeh",
  "score" : "112-108"
}, {
  "homeTeam" : "AL Sharjah",
  "awayTeam" : "AL Nasr (Bae)",
  "score" : "83-90"
}, {
  "homeTeam" : "Shanghai S.",
  "awayTeam" : "Zhejiang L.",
  "score" : "91-88"
}, {
  "homeTeam" : "Pelita Jaya Bakrie Jakarta",
  "awayTeam" : "Rans Pik",
  "score" : "98-57"
}, {
  "homeTeam" : "Tangerang Hawks",
  "awayTeam" : "Dewa Utd Surabaya",
  "score" : "66-85"
}, {
  "homeTeam" : "Lietkabelis",
  "awayTeam" : "Zalgiris Kaunas",
  "score" : "75-95"
}, {
  "homeTeam" : "CSM Oradea",
  "awayTeam" : "Cluj Napoca",
  "score" : "83-88"
}, {
  "homeTeam" : "Da Nang Dragons",
  "awayTeam" : "Ho Chi Minh City Wings",
  "score" : "82-95"
}, {
  "homeTeam" : "Unics Kazan",
  "awayTeam" : "Zenit",
  "score" : "64-55"
}, {
  "homeTeam" : "Panathinaikos",
  "awayTeam" : "PAOK",
  "score" : "114-102"
} ]