[ {
  "homeTeam" : "Philadelphia",
  "awayTeam" : "Sacramento",
  "score" : "113-111"
}, {
  "homeTeam" : "Washington",
  "awayTeam" : "Milwaukee",
  "score" : "109-99"
}, {
  "homeTeam" : "Atlanta",
  "awayTeam" : "Houston",
  "score" : "86-104"
}, {
  "homeTeam" : "Chicago",
  "awayTeam" : "Miami",
  "score" : "113-116"
}, {
  "homeTeam" : "Dallas",
  "awayTeam" : "Charlotte",
  "score" : "121-123"
}, {
  "homeTeam" : "Phoenix",
  "awayTeam" : "Detroit",
  "score" : "114-96"
}, {
  "homeTeam" : "Denver",
  "awayTeam" : "Brooklyn",
  "score" : "107-103"
}, {
  "homeTeam" : "Minnesota",
  "awayTeam" : "Oklahoma",
  "score" : "123-111"
}, {
  "homeTeam" : "Purdue Boilermakers (K)",
  "awayTeam" : "Michigan St Spartans (K)",
  "score" : "65-86"
}, {
  "homeTeam" : "Boston College Eagles (K)",
  "awayTeam" : "North Carolina State (K)",
  "score" : "84-106"
}, {
  "homeTeam" : "Virginia Tech Hokies (K)",
  "awayTeam" : "Pittsburgh Panthers (K)",
  "score" : "67-50"
}, {
  "homeTeam" : "TCU Horned Frogs (K)",
  "awayTeam" : "Kansas Jayhawks (K)",
  "score" : "79-77"
}, {
  "homeTeam" : "Georgia Bulldogs (K)",
  "awayTeam" : "Alabama Crimson (K)",
  "score" : "53-68"
}, {
  "homeTeam" : "Oklahoma Sooners (K)",
  "awayTeam" : "A&M Aggies (K)",
  "score" : "85-58"
}, {
  "homeTeam" : "Florida Gators (K)",
  "awayTeam" : "Texas Longhorns (K)",
  "score" : "68-88"
}, {
  "homeTeam" : "Ohio State Buckeyes (K)",
  "awayTeam" : "Wisconsin Bad (K)",
  "score" : "81-58"
}, {
  "homeTeam" : "LSU Tigers (K)",
  "awayTeam" : "Arkansas Razorbacks(K)",
  "score" : "92-70"
}, {
  "homeTeam" : "Miami Hurricanes (K)",
  "awayTeam" : "Duke Blue Devils (K)",
  "score" : "58-74"
}, {
  "homeTeam" : "Auburn Tigers (K)",
  "awayTeam" : "South Carolina (K)",
  "score" : "51-81"
}, {
  "homeTeam" : "USC Trojans (K)",
  "awayTeam" : "Iowa Hawk (K)",
  "score" : "81-69"
}, {
  "homeTeam" : "Iowa State Cyclones",
  "awayTeam" : "Colorado Buf",
  "score" : "97-67"
}, {
  "homeTeam" : "Illinois Fighting Illini",
  "awayTeam" : "Washington Huskies",
  "score" : "75-66"
}, {
  "homeTeam" : "Paisas Basktball",
  "awayTeam" : "Astros",
  "score" : "59-87"
}, {
  "homeTeam" : "CA San Lorenzo De Almagro",
  "awayTeam" : "Independiente de Oliva",
  "score" : "69-80"
}, {
  "homeTeam" : "CA Cordon",
  "awayTeam" : "Defensor Sporting",
  "score" : "84-90"
}, {
  "homeTeam" : "Club Un. At",
  "awayTeam" : "Club Bigua De Villa Biarritz",
  "score" : "86-79"
}, {
  "homeTeam" : "OGM Ormanspor (K)",
  "awayTeam" : "ÇBK Mersin (K)",
  "score" : "62-115"
}, {
  "homeTeam" : "N. Z. Breakers",
  "awayTeam" : "Melbourne U.",
  "score" : "97-95"
}, {
  "homeTeam" : "Cairns Taipans",
  "awayTeam" : "Tasmania Jackjumpers",
  "score" : "96-93"
}, {
  "homeTeam" : "Geelong Supe (K)",
  "awayTeam" : "Bendigo Spirit (K)",
  "score" : "80-73"
}, {
  "homeTeam" : "Nanjing M.K.",
  "awayTeam" : "Sichuan B.W.",
  "score" : "104-72"
}, {
  "homeTeam" : "Beijing R. F.",
  "awayTeam" : "Qingdao E.",
  "score" : "69-64"
}, {
  "homeTeam" : "Shanghai S.",
  "awayTeam" : "Shenzhen Leopards",
  "score" : "101-92"
}, {
  "homeTeam" : "West Bandits Solo",
  "awayTeam" : "Satya Wacana LBC",
  "score" : "99-62"
}, {
  "homeTeam" : "Satria Muda Pertamina Jakarta",
  "awayTeam" : "Pacific Caesar Surabaya",
  "score" : "106-56"
}, {
  "homeTeam" : "Bucheon Hana (K)",
  "awayTeam" : "Busan BNK Sum (K)",
  "score" : "67-58"
}, {
  "homeTeam" : "Dongbu Promy",
  "awayTeam" : "Daegu Pegasus",
  "score" : "108-103"
}, {
  "homeTeam" : "Ehime O. V.",
  "awayTeam" : "Rizing Fukuoka",
  "score" : "77-85"
}, {
  "homeTeam" : "Tropang Giga",
  "awayTeam" : "San Miguel",
  "score" : "82-96"
}, {
  "homeTeam" : "Keelung Black Kites",
  "awayTeam" : "Taiwan Beer",
  "score" : "92-81"
}, {
  "homeTeam" : "Changhua Bll",
  "awayTeam" : "YL Dinos",
  "score" : "65-69"
}, {
  "homeTeam" : "AL Faisaly (Ürd)",
  "awayTeam" : "Amman Utd",
  "score" : "67-83"
} ]